tx_highered/__init__.py
tx_highered/__init__.py-r
tx_highered/admin.py
tx_highered/api.py
tx_highered/factories.py
tx_highered/ipeds_csv_reader.py
tx_highered/urls.py
tx_highered/views.py
tx_highered/fixtures/highered_base.json
tx_highered/fixtures/highered_base_alt.json
tx_highered/fixtures/tx_highered_2012.json.gz
tx_highered/instachart/__init__.py
tx_highered/instachart/models.py
tx_highered/instachart/README.md
tx_highered/instachart/templates/instachart/simplechart/simple_chart.html
tx_highered/instachart/templatetags/__init__.py
tx_highered/instachart/templatetags/instachart.py
tx_highered/management/__init__.py
tx_highered/management/commands/__init__.py
tx_highered/management/commands/tx_highered_import.py
tx_highered/management/commands/tx_highered_process.py
tx_highered/management/commands/tx_highered_reportcard.py
tx_highered/migrations/0001_initial.py
tx_highered/migrations/0002_auto__add_field_system_location__add_field_institution_location.py
tx_highered/migrations/0003_auto__add_publicenrollment__add_unique_publicenrollment_year_instituti.py
tx_highered/migrations/0004_auto__add_publicgraduationrates__add_unique_publicgraduationrates_year.py
tx_highered/migrations/0005_auto__add_publicadmissions__add_unique_publicadmissions_year_instituti.py
tx_highered/migrations/__init__.py
tx_highered/models/__init__.py
tx_highered/models/base.py
tx_highered/models/reports.py
tx_highered/models/thecb.py
tx_highered/scripts/2014_update.py
tx_highered/scripts/__init__.py
tx_highered/scripts/import_customreport.py
tx_highered/scripts/import_thecb_report.py
tx_highered/scripts/init_institutions.py
tx_highered/scripts/init_ipeds_ids.py
tx_highered/scripts/init_wikipedia.py
tx_highered/scripts/utils.py
tx_highered/static/d3/js/d3.v2.js
tx_highered/static/d3/js/d3.v2.min.js
tx_highered/static/js/bootstrap-tooltip-d3.js
tx_highered/static/js/jquery.onionskin.js
tx_highered/static/js/jquery.tablebars.js
tx_highered-0.3.5.dist-info/DESCRIPTION.rst
tx_highered-0.3.5.dist-info/METADATA
tx_highered-0.3.5.dist-info/metadata.json
tx_highered-0.3.5.dist-info/RECORD
tx_highered-0.3.5.dist-info/top_level.txt
tx_highered-0.3.5.dist-info/WHEEL
tx_highered-0.3.5.dist-info/zip-safe
