Metadata-Version: 2.0
Name: tx-highered
Version: 0.3.5
Summary: Django app for Texas higher education data
Home-page: http://github.com/texastribune/tx_highered/
Author: Texas Tribune
Author-email: tech@texastribune.org
License: Apache Software License
Platform: UNKNOWN
Classifier: Development Status :: 4 - Beta
Classifier: Environment :: Web Environment
Classifier: Framework :: Django
Classifier: Intended Audience :: Developers
Classifier: License :: OSI Approved :: Apache Software License
Classifier: Operating System :: OS Independent
Classifier: Programming Language :: Python
Classifier: Topic :: Other/Nonlisted Topic
Requires-Dist: tx-lege-districts (>=0.4.0)
